tonepilot/__init__.py
tonepilot/cli/__init__.py
tonepilot/cli/cli.py
tonepilot/config/personality_library.yaml
tonepilot/core/__init__.py
tonepilot/core/tonepilot.py
tonepilot/factory/__init__.py
tonepilot/factory/responder_factory.py
tonepilot/factory/tagger_factory.py
tonepilot/responders/__init__.py
tonepilot/responders/base_responder.py
tonepilot/responders/gemini_responder.py
tonepilot/responders/huggingface_responder.py
tonepilot/responders/prompt_builder.py
tonepilot/taggers/__init__.py
tonepilot/taggers/base_tagger.py
tonepilot/taggers/gemini_tagger.py
tonepilot/taggers/hf_tagger.py
tonepilot/taggers/zero_shot_tagger.py
tonepilot/tonemapper/tonemapper.py
tonepilot-0.1.2.dist-info/licenses/LICENSE
tonepilot-0.1.2.dist-info/METADATA
tonepilot-0.1.2.dist-info/WHEEL
tonepilot-0.1.2.dist-info/entry_points.txt
tonepilot-0.1.2.dist-info/top_level.txt
tonepilot-0.1.2.dist-info/RECORD
