Metadata-Version: 2.4
Name: tonepilot
Version: 0.1.2
Summary: Emotional intelligence for text generation - detect emotional tones and generate contextually appropriate responses
Author-email: Srivani Durgi <sdurgi21@gmail.com>
Maintainer-email: Srivani Durgi <sdurgi21@gmail.com>
License: MIT
Project-URL: Repository, https://github.com/sdurgi/tonepilot
Project-URL: Bug Tracker, https://github.com/sdurgi/tonepilot/issues
Keywords: emotion,nlp,ai,text-generation,emotional-intelligence,sentiment-analysis,transformers
Classifier: Development Status :: 3 - Alpha
Classifier: Intended Audience :: Developers
Classifier: Intended Audience :: Science/Research
Classifier: License :: OSI Approved :: MIT License
Classifier: Operating System :: OS Independent
Classifier: Programming Language :: Python :: 3
Classifier: Programming Language :: Python :: 3.8
Classifier: Programming Language :: Python :: 3.9
Classifier: Programming Language :: Python :: 3.10
Classifier: Programming Language :: Python :: 3.11
Classifier: Programming Language :: Python :: 3.12
Classifier: Topic :: Scientific/Engineering :: Artificial Intelligence
Classifier: Topic :: Text Processing :: Linguistic
Classifier: Topic :: Software Development :: Libraries :: Python Modules
Requires-Python: >=3.8
License-File: LICENSE
Requires-Dist: transformers>=4.20.0
Requires-Dist: torch>=1.9.0
Requires-Dist: google-generativeai>=0.3.0
Requires-Dist: python-dotenv>=0.19.0
Requires-Dist: PyYAML>=6.0
Requires-Dist: scikit-learn>=1.0.0
Provides-Extra: dev
Requires-Dist: pytest>=7.0.0; extra == "dev"
Requires-Dist: pytest-cov>=4.0.0; extra == "dev"
Requires-Dist: black>=22.0.0; extra == "dev"
Requires-Dist: flake8>=5.0.0; extra == "dev"
Requires-Dist: mypy>=1.0.0; extra == "dev"
Requires-Dist: pre-commit>=2.20.0; extra == "dev"
Provides-Extra: docs
Requires-Dist: sphinx>=5.0.0; extra == "docs"
Requires-Dist: sphinx-rtd-theme>=1.0.0; extra == "docs"
Requires-Dist: myst-parser>=0.18.0; extra == "docs"
Dynamic: license-file
